[
  {
    "id": null,
    "fieldName": null,
    "name": "Declaración",
    "description": null,
    "helpText": null,
    "listItemPrefix": null,
    "choices": null,
    "type": "formTitle"
  },
  {
    "id": 1,
    "fieldName": null,
    "name": null,
    "description": null,
    "helpText": null,
    "listItemPrefix": null,
    "choices": null,
    "type": "section"
  },
  {
    "id": 25,
    "fieldName": "q25__h5_Thank_you_for_completing_t",
    "name": "Gracias por rellenar el cuestionario. Sus respuestas serán revisadas por el equipo de Grünenthal.",
    "description": "Gracias por rellenar el cuestionario. Sus respuestas serán revisadas por el equipo de Grünenthal.",
    "helpText": null,
    "listItemPrefix": null,
    "choices": null,
    "type": "field"
  },
  {
    "id": 37,
    "fieldName": null,
    "name": null,
    "description": "Declaración de privacidad de datos para socios comerciales, proveedores y otros terceros | Grünenthal (grunenthal.com)",
    "helpText": null,
    "listItemPrefix": null,
    "choices": null,
    "type": "field"
  },
  {
    "id": 40,
    "fieldName": null,
    "name": null,
    "description": "Al enviar este formulario, confirmo que toda la información facilitada es exacta. Me comprometo a informar puntualmente a Grünenthal, durante la vigencia de la relación comercial, de cualquier modificación sustancial de la información facilitada en este cuestionario.",
    "helpText": null,
    "listItemPrefix": null,
    "choices": null,
    "type": "field"
  },
  {
    "id": 4,
    "fieldName": "_p__br___p_",
    "name": "N.º",
    "description": null,
    "helpText": null,
    "listItemPrefix": null,
    "choices": {
      "I have read and understood the Privacy Notice to be found in this document (see separate sheet) and herewith confirm that I am entitled to provide to Grünenthal the information contained in this questionnaire. If applicable, I will inform the data subjects the information in this questionnaire relates to about their data privacy rights according to Art. 13, 14 of the EU General Data Protection Regulation (“GDPR”), e.g. by forwarding the privacy notice to them.": ""
    },
    "type": "field"
  },
  {
    "id": 46,
    "fieldName": "q46__p__span_style__color__rgb_62_",
    "name": "Declaración de confidencialidad",
    "description": null,
    "helpText": null,
    "listItemPrefix": null,
    "choices": null,
    "type": "field"
  },
  {
    "id": 13,
    "fieldName": "q13__p_Would_you_like_to_provide_y",
    "name": "¿Desea facilitar las Condiciones   que utiliza su empresa?",
    "description": null,
    "helpText": null,
    "listItemPrefix": null,
    "choices": null,
    "type": "field"
  },
  {
    "id": 16,
    "fieldName": "q16__p_Please_upload_Terms__amp__C",
    "name": "Por favor, suba los Términos  Condiciones que utiliza su empresa",
    "description": null,
    "helpText": null,
    "listItemPrefix": null,
    "choices": null,
    "type": "field"
  },
  {
    "id": 19,
    "fieldName": "_p_Please_provide_a_reason__p_",
    "name": "Indique el motivo",
    "description": null,
    "helpText": null,
    "listItemPrefix": null,
    "choices": null,
    "type": "field"
  },
  {
    "id": 10,
    "fieldName": "q10__p_I_acknowledge_that_I_had_re",
    "name": "Reconozco que he leído y acepto las directrices anteriores",
    "description": null,
    "helpText": null,
    "listItemPrefix": null,
    "choices": null,
    "type": "field"
  }
]